{
 "NVDA": {
  "ticker": "NVDA",
  "price": 200.09,
  "currency": "USD",
  "chg1d": 2.63,
  "high52": 235.74,
  "low52": 153.3,
  "fromHigh": -15.1,
  "fromLow": 30.5,
  "pos": "中位",
  "posPct": 57,
  "date": "2026-07-01"
 },
 "MSFT": {
  "ticker": "MSFT",
  "price": 373.02,
  "currency": "USD",
  "chg1d": 1.21,
  "high52": 542.07,
  "low52": 352.83,
  "fromHigh": -31.2,
  "fromLow": 5.7,
  "pos": "低位",
  "posPct": 11,
  "date": "2026-07-01"
 },
 "7203.T": {
  "ticker": "7203.T",
  "price": 2725,
  "currency": "JPY",
  "chg1d": -1.7,
  "high52": 3944,
  "low52": 2453,
  "fromHigh": -30.9,
  "fromLow": 11.1,
  "pos": "低位",
  "posPct": 18,
  "date": "2026-07-01"
 },
 "6758.T": {
  "ticker": "6758.T",
  "price": 3280,
  "currency": "JPY",
  "chg1d": -0.58,
  "high52": 4700,
  "low52": 3113,
  "fromHigh": -30.2,
  "fromLow": 5.4,
  "pos": "低位",
  "posPct": 11,
  "date": "2026-07-01"
 },
 "0700.HK": {
  "ticker": "0700.HK",
  "price": 429.8,
  "currency": "HKD",
  "chg1d": 2.28,
  "high52": 677.5,
  "low52": 411.8,
  "fromHigh": -36.6,
  "fromLow": 4.4,
  "pos": "低位",
  "posPct": 7,
  "date": "2026-07-01"
 },
 "TEM": {
  "ticker": "TEM",
  "price": 57.93,
  "currency": "USD",
  "chg1d": -0.65,
  "high52": 103.25,
  "low52": 42.37,
  "fromHigh": -43.9,
  "fromLow": 36.7,
  "pos": "低位",
  "posPct": 26,
  "date": "2026-07-01"
 },
 "FATE": {
  "ticker": "FATE",
  "price": 2.7,
  "currency": "USD",
  "chg1d": 11.57,
  "high52": 2.84,
  "low52": 0.92,
  "fromHigh": -4.9,
  "fromLow": 193.5,
  "pos": "高位",
  "posPct": 93,
  "date": "2026-07-01"
 },
 "01729": {
  "ticker": "01729",
  "error": "行情获取失败 01729 HTTP 404"
 },
 "CLS": {
  "ticker": "CLS",
  "price": 364.8,
  "currency": "USD",
  "chg1d": 6.28,
  "high52": 472.4,
  "low52": 148.91,
  "fromHigh": -22.8,
  "fromLow": 145,
  "pos": "高位",
  "posPct": 67,
  "date": "2026-07-01"
 },
 "COHR": {
  "ticker": "COHR",
  "price": 394.47,
  "currency": "USD",
  "chg1d": 0.83,
  "high52": 426.89,
  "low52": 86.55,
  "fromHigh": -7.6,
  "fromLow": 355.8,
  "pos": "高位",
  "posPct": 90,
  "date": "2026-07-01"
 },
 "PWR": {
  "ticker": "PWR",
  "price": 720.04,
  "currency": "USD",
  "chg1d": 0.78,
  "high52": 785.24,
  "low52": 372.29,
  "fromHigh": -8.3,
  "fromLow": 93.4,
  "pos": "高位",
  "posPct": 84,
  "date": "2026-07-01"
 },
 "IRM": {
  "ticker": "IRM",
  "price": 126.31,
  "currency": "USD",
  "chg1d": -2.82,
  "high52": 133.06,
  "low52": 78.86,
  "fromHigh": -5.1,
  "fromLow": 60.2,
  "pos": "高位",
  "posPct": 88,
  "date": "2026-07-01"
 },
 "NBIS": {
  "ticker": "NBIS",
  "price": 276.17,
  "currency": "USD",
  "chg1d": 5.75,
  "high52": 286.69,
  "low52": 44.3,
  "fromHigh": -3.7,
  "fromLow": 523.4,
  "pos": "高位",
  "posPct": 96,
  "date": "2026-07-01"
 },
 "CRDO": {
  "ticker": "CRDO",
  "price": 271.95,
  "currency": "USD",
  "chg1d": 10.69,
  "high52": 302.52,
  "low52": 87.59,
  "fromHigh": -10.1,
  "fromLow": 210.5,
  "pos": "高位",
  "posPct": 86,
  "date": "2026-07-01"
 },
 "SYM": {
  "ticker": "SYM",
  "price": 44.95,
  "currency": "USD",
  "chg1d": 6.67,
  "high52": 87.3,
  "low52": 38.57,
  "fromHigh": -48.5,
  "fromLow": 16.5,
  "pos": "低位",
  "posPct": 13,
  "date": "2026-07-01"
 },
 "MU": {
  "ticker": "MU",
  "price": 1154.29,
  "currency": "USD",
  "chg1d": 0.79,
  "high52": 1213.56,
  "low52": 104.88,
  "fromHigh": -4.9,
  "fromLow": 1000.6,
  "pos": "高位",
  "posPct": 95,
  "date": "2026-07-01"
 },
 "7974.T": {
  "ticker": "7974.T",
  "price": 6815,
  "currency": "JPY",
  "chg1d": -1.73,
  "high52": 14655,
  "low52": 6589,
  "fromHigh": -53.5,
  "fromLow": 3.4,
  "pos": "低位",
  "posPct": 3,
  "date": "2026-07-01"
 },
 "LULU": {
  "ticker": "LULU",
  "price": 114.18,
  "currency": "USD",
  "chg1d": -0.1,
  "high52": 247.68,
  "low52": 105.43,
  "fromHigh": -53.9,
  "fromLow": 8.3,
  "pos": "低位",
  "posPct": 6,
  "date": "2026-07-01"
 },
 "CRWV": {
  "ticker": "CRWV",
  "price": 99.54,
  "currency": "USD",
  "chg1d": 4.22,
  "high52": 165.2,
  "low52": 64.55,
  "fromHigh": -39.7,
  "fromLow": 54.2,
  "pos": "中位",
  "posPct": 35,
  "date": "2026-07-01"
 },
 "RDDT": {
  "ticker": "RDDT",
  "price": 173.58,
  "currency": "USD",
  "chg1d": -0.46,
  "high52": 270.71,
  "low52": 121.84,
  "fromHigh": -35.9,
  "fromLow": 42.5,
  "pos": "中位",
  "posPct": 35,
  "date": "2026-07-01"
 }
}